setup.py
pyloy/__init__.py
pyloy/pymenu.py
pyloy.egg-info/PKG-INFO
pyloy.egg-info/SOURCES.txt
pyloy.egg-info/dependency_links.txt
pyloy.egg-info/top_level.txt