Metadata-Version: 2.1
Name: pyloy
Version: 0.0.1
Summary: Load GUI in terminal
Author: cdg
